tmath/__init__.py
tmath-0.4.dist-info/LICENCE.txt
tmath-0.4.dist-info/METADATA
tmath-0.4.dist-info/WHEEL
tmath-0.4.dist-info/top_level.txt
tmath-0.4.dist-info/RECORD
