Metadata-Version: 2.1
Name: tmath
Version: 0.4
Summary: Only for demo purpose add, sub, mul, div and squ
Author: Tushali Devikar
Author-email: tushalidevikar1997@gmail.com
Classifier: Programming Language :: Python :: 3
Classifier: License :: OSI Approved :: MIT License
Classifier: Operating System :: OS Independent
License-File: LICENCE.txt
